hydro_roll-0.1.10.dist-info/METADATA
hydro_roll-0.1.10.dist-info/WHEEL
hydro_roll-0.1.10.dist-info/entry_points.txt
hydro_roll-0.1.10.dist-info/licenses/LICENSE
hydro_roll-0.1.10.dist-info/licenses/LICENSE-2
hydro_roll-0.1.10.dist-info/licenses/LICENSE-3
hydro_roll-0.1.10.dist-info/licenses/LICENSE-4
hydro_roll/config.py
hydro_roll/__init__.py
hydro_roll/models/__init__.py
hydro_roll/models/hola.pkl
hydro_roll/models/utils.py
hydro_roll/cli.py
hydro_roll/utils.py
hydro_roll/exceptions.py
hydro_roll/typing.py
hydro_roll/hydro_roll.abi3.so
hydro_roll-0.1.10.dist-info/RECORD
