Metadata-Version: 2.3
Name: hydro-roll
Version: 0.1.10
Classifier: Development Status :: 5 - Production/Stable
Classifier: Framework :: Robot Framework
Classifier: Framework :: Robot Framework :: Library
Classifier: Operating System :: OS Independent
Classifier: Programming Language :: Python :: 3
Classifier: Programming Language :: Rust
Classifier: Programming Language :: Python :: Implementation :: CPython
Classifier: Programming Language :: Python :: Implementation :: PyPy
Requires-Dist: watchfiles <1.0.0, >=0.18.0
Requires-Dist: joblib >=1.3.2
Requires-Dist: randomgen >=1.26.0
Requires-Dist: jieba >=0.42.1
Requires-Dist: scikit-learn >=1.3.1
Requires-Dist: requests >=2.31.0
Requires-Dist: apscheduler >=3.10.4
Requires-Dist: lupa >=2.1
Requires-Dist: lark >=1.1.8
Requires-Dist: cachetools >=5.3.2
Requires-Dist: iamai[onebot11] >=0.0.2
Requires-Dist: matplotlib >=3.8.4
License-File: LICENSE
License-File: LICENSE-2
License-File: LICENSE-3
License-File: LICENSE-4
Summary: 跨平台、多模态、高度自定义的骰系开发框架。
Keywords: bot,qq,qqbot,mirai,coolq,gensokyo,dice,hydroroll
Home-Page: https://hydroroll.team/
Author: HsiangNianian
Author-email: HsiangNianian <i@jyunko.cn>
License: MIT
Requires-Python: >=3.9
Project-URL: homepage, https://hydroroll.team/
Project-URL: repository, https://github.com/HydroRoll-Team/HydroRoll
Project-URL: documentation, https://docs.hydroroll.team/
